[
    { "name": "Adelle Sans Devanagari", "id": "adelle-sans-devanagari" },
    { "name": "Aharoni", "id": "aharoni" },
    { "name": "Al Bayan", "id": "al-bayan" },
    { "name": "Al Firat", "id": "al-firat" },
    { "name": "Al Khalil", "id": "al-khalil" },
    { "name": "Al Nile", "id": "al-nile" },
    { "name": "Al Rafidain Al Fanni", "id": "al-rafidain-al-fanni" },
    { "name": "Al Rafidain", "id": "al-rafidain" },
    { "name": "Al Tarikh", "id": "al-tarikh" },
    { "name": "Aldhabi", "id": "aldhabi" },
    { "name": "Algiers", "id": "algiers" },
    { "name": "American Typewriter", "id": "american-typewriter" },
    { "name": "Andalé Mono", "id": "andalé-mono" },
    { "name": "Andalus", "id": "andalus" },
    { "name": "Angsana New", "id": "angsana-new" },
    { "name": "AngsanaUPC", "id": "angsanaupc" },
    { "name": "Ani", "id": "ani" },
    { "name": "AnjaliOldLipi", "id": "anjalioldlipi" },
    { "name": "Annai MN", "id": "annai-mn" },
    { "name": "Aparajita", "id": "aparajita" },
    { "name": "Apple Braille", "id": "apple-braille" },
    { "name": "Apple Casual", "id": "apple-casual" },
    { "name": "Apple Chancery", "id": "apple-chancery" },
    { "name": "Apple Garamond", "id": "apple-garamond" },
    { "name": "Apple Gothic", "id": "apple-gothic" },
    { "name": "Apple LiGothic", "id": "apple-ligothic" },
    { "name": "Apple LiSung", "id": "apple-lisung" },
    { "name": "Apple Myungjo", "id": "apple-myungjo" },
    { "name": "Apple SD Gothic Neo", "id": "apple-sd-gothic-neo" },
    { "name": "AquaKana", "id": "aquakana" },
    { "name": "Arabic Typesetting", "id": "arabic-typesetting" },
    { "name": "Arial Hebrew Scholar", "id": "arial-hebrew-scholar" },
    { "name": "Arial Hebrew", "id": "arial-hebrew" },
    { "name": "Arial Narrow", "id": "arial-narrow" },
    { "name": "Arial Nova", "id": "arial-nova" },
    { "name": "Arial Unicode MS", "id": "arial-unicode-ms" },
    { "name": "Arial", "id": "arial" },
    { "name": "Avenir", "id": "avenir" },
    { "name": "Ayuthaya", "id": "ayuthaya" },
    { "name": "Baghdad", "id": "baghdad" },
    { "name": "Bahnschrift", "id": "bahnschrift" },
    { "name": "Baloo Bhai", "id": "baloo-bhai" },
    { "name": "Baloo Bhaijaan", "id": "baloo-bhaijaan" },
    { "name": "Baloo Bhaina", "id": "baloo-bhaina" },
    { "name": "Baloo Chettan", "id": "baloo-chettan" },
    { "name": "Baloo Da", "id": "baloo-da" },
    { "name": "Baloo Paaji", "id": "baloo-paaji" },
    { "name": "Baloo Tamma", "id": "baloo-tamma" },
    { "name": "Baloo Tammudu", "id": "baloo-tammudu" },
    { "name": "Baloo Thambi", "id": "baloo-thambi" },
    { "name": "Baloo", "id": "baloo" },
    { "name": "Bangla MN", "id": "bangla-mn" },
    { "name": "Bangla Sangam MN", "id": "bangla-sangam-mn" },
    { "name": "Baoli SC", "id": "baoli-sc" },
    { "name": "Baoli TC", "id": "baoli-tc" },
    { "name": "Baskerville", "id": "baskerville" },
    { "name": "Basra", "id": "basra" },
    { "name": "Batang", "id": "batang" },
    { "name": "Beijing", "id": "beijing" },
    { "name": "Beirut", "id": "beirut" },
    { "name": "BiauKai", "id": "biaukai" },
    { "name": "Big Caslon", "id": "big-caslon" },
    { "name": "Bitstream Charter", "id": "bitstream-charter" },
    { "name": "BIZ UDGothic", "id": "biz-udgothic" },
    { "name": "BIZ UDMincho", "id": "biz-udmincho" },
    { "name": "Bodoni 72", "id": "bodoni-72" },
    { "name": "Braganza", "id": "braganza" },
    { "name": "Browallia New", "id": "browallia-new" },
    { "name": "BrowalliaUPC", "id": "browalliaupc" },
    { "name": "Brush Script", "id": "brush-script" },
    { "name": "Calibri", "id": "calibri" },
    { "name": "Cambay Devanagari", "id": "cambay-devanagari" },
    { "name": "Cambria", "id": "cambria" },
    { "name": "Candara", "id": "candara" },
    { "name": "Canela Deck", "id": "canela-deck" },
    { "name": "Canela", "id": "canela" },
    { "name": "Cantarell", "id": "cantarell" },
    { "name": "Capitals", "id": "capitals" },
    { "name": "Century Gothic", "id": "century-gothic" },
    { "name": "Century Schoolbook L", "id": "century-schoolbook-l" },
    { "name": "Century Schoolbook", "id": "century-schoolbook" },
    { "name": "Chalkboard", "id": "chalkboard" },
    { "name": "Chalkduster", "id": "chalkduster" },
    { "name": "Chandas", "id": "chandas" },
    { "name": "Charcoal CY", "id": "charcoal-cy" },
    { "name": "Charcoal", "id": "charcoal" },
    { "name": "Charter Roman", "id": "charter-roman" },
    { "name": "Chicago", "id": "chicago" },
    { "name": "Chilanka", "id": "chilanka" },
    { "name": "Cochin", "id": "cochin" },
    { "name": "Comic Sans MS", "id": "comic-sans-ms" },
    { "name": "Comic Sans", "id": "comic-sans" },
    { "name": "Consolas", "id": "consolas" },
    { "name": "Constantia", "id": "constantia" },
    { "name": "Copperplate", "id": "copperplate" },
    { "name": "Corbel", "id": "corbel" },
    { "name": "Cordia New", "id": "cordia-new" },
    { "name": "CordiaUPC", "id": "cordiaupc" },
    { "name": "Corsiva Hebrew", "id": "corsiva-hebrew" },
    { "name": "Courier New", "id": "courier-new" },
    { "name": "Courier", "id": "courier" },
    { "name": "Damascus", "id": "damascus" },
    { "name": "DaunPenh", "id": "daunpenh" },
    { "name": "David", "id": "david" },
    { "name": "Dear Joe Four", "id": "dear-joe-four" },
    { "name": "DecoType Naskh", "id": "decotype-naskh" },
    { "name": "DengXian", "id": "dengxian" },
    { "name": "Devanagari MT", "id": "devanagari-mt" },
    { "name": "Devanagari Sangam MN", "id": "devanagari-sangam-mn" },
    { "name": "Devanagari", "id": "devanagari" },
    { "name": "DFKai-SB", "id": "dfkai-sb" },
    { "name": "Didot", "id": "didot" },
    { "name": "Dijla", "id": "dijla" },
    { "name": "DilleniaUPC", "id": "dilleniaupc" },
    { "name": "Diwan Kufi", "id": "diwan-kufi" },
    { "name": "Diwan Thuluth", "id": "diwan-thuluth" },
    { "name": "DokChampa", "id": "dokchampa" },
    { "name": "Domaine Display", "id": "domaine-display" },
    { "name": "Dotum", "id": "dotum" },
    { "name": "Droid Sans Fallback", "id": "droid-sans-fallback" },
    { "name": "Droid Sans Mono", "id": "droid-sans-mono" },
    { "name": "Droid Sans", "id": "droid-sans" },
    { "name": "Droid Serif", "id": "droid-serif" },
    { "name": "Dyuthi", "id": "dyuthi" },
    { "name": "Ebrima", "id": "ebrima" },
    { "name": "Estrangelo Edessa", "id": "estrangelo-edessa" },
    { "name": "EucrosiaUPC", "id": "eucrosiaupc" },
    { "name": "Euphemia UCAS", "id": "euphemia-ucas" },
    { "name": "Euphemia", "id": "euphemia" },
    { "name": "FangSong", "id": "fangsong" },
    { "name": "Farah", "id": "farah" },
    { "name": "Farisi", "id": "farisi" },
    { "name": "Forgotten Futurist", "id": "forgotten-futurist" },
    { "name": "Founders Grotesk", "id": "founders-grotesk" },
    { "name": "Franklin Gothic", "id": "franklin-gothic" },
    { "name": "FrankRuehl", "id": "frankruehl" },
    { "name": "FreesiaUPC", "id": "freesiaupc" },
    { "name": "Futura", "id": "futura" },
    { "name": "Gabriola", "id": "gabriola" },
    { "name": "Gadget", "id": "gadget" },
    { "name": "Gadugi", "id": "gadugi" },
    { "name": "Galvji", "id": "galvji" },
    { "name": "Garamond", "id": "garamond" },
    { "name": "Garuda", "id": "garuda" },
    { "name": "Gautami", "id": "gautami" },
    { "name": "Gayathri", "id": "gayathri" },
    { "name": "GB18030 Bitmap", "id": "gb18030-bitmap" },
    { "name": "Geeza Pro", "id": "geeza-pro" },
    { "name": "Geezah", "id": "geezah" },
    { "name": "Geneva CY", "id": "geneva-cy" },
    { "name": "Geneva", "id": "geneva" },
    { "name": "Georgia Pro", "id": "georgia-pro" },
    { "name": "Georgia", "id": "georgia" },
    { "name": "Gill Sans Nova", "id": "gill-sans-nova" },
    { "name": "Gill Sans", "id": "gill-sans" },
    { "name": "Gisha", "id": "gisha" },
    { "name": "Gotu", "id": "gotu" },
    { "name": "Graphik", "id": "graphik" },
    { "name": "Gubbi", "id": "gubbi" },
    { "name": "Gujarati MT", "id": "gujarati-mt" },
    { "name": "Gujarati Sangam MN", "id": "gujarati-sangam-mn" },
    { "name": "Gujarati", "id": "gujarati" },
    { "name": "Gulim", "id": "gulim" },
    { "name": "Gung Seoche", "id": "gung-seoche" },
    { "name": "GungSeo", "id": "gungseo" },
    { "name": "Gungsuh", "id": "gungsuh" },
    { "name": "Gurmukhi MN", "id": "gurmukhi-mn" },
    { "name": "Gurmukhi MT", "id": "gurmukhi-mt" },
    { "name": "Gurmukhi Sangam MN", "id": "gurmukhi-sangam-mn" },
    { "name": "Gurmukhi", "id": "gurmukhi" },
    { "name": "Hangangche", "id": "hangangche" },
    { "name": "Hannotate SC", "id": "hannotate-sc" },
    { "name": "Hannotate TC", "id": "hannotate-tc" },
    { "name": "HanziPen SC", "id": "hanzipen-sc" },
    { "name": "HanziPen TC", "id": "hanzipen-tc" },
    { "name": "HeadlineA", "id": "headlinea" },
    { "name": "Hei", "id": "hei" },
    { "name": "Heiti SC", "id": "heiti-sc" },
    { "name": "Helvetica CY", "id": "helvetica-cy" },
    { "name": "Helvetica Neue", "id": "helvetica-neue" },
    { "name": "Helvetica", "id": "helvetica" },
    { "name": "Herculanum", "id": "herculanum" },
    { "name": "Hiragino Kaku Gothic Pro", "id": "hiragino-kaku-gothic-pro" },
    { "name": "Hiragino Kaku Gothic", "id": "hiragino-kaku-gothic" },
    { "name": "Hiragino Maru Gothic Pro", "id": "hiragino-maru-gothic-pro" },
    { "name": "Hiragino Mincho Pro", "id": "hiragino-mincho-pro" },
    { "name": "Hiragino Sans", "id": "hiragino-sans" },
    { "name": "Hoefler Text", "id": "hoefler-text" },
    { "name": "Hopper Script", "id": "hopper-script" },
    { "name": "Inai Mathi", "id": "inai-mathi" },
    { "name": "Ink Free", "id": "ink-free" },
    { "name": "Iowan Old Style Titling", "id": "iowan-old-style-titling" },
    { "name": "IrisUPC", "id": "irisupc" },
    { "name": "Iskoola Pota", "id": "iskoola-pota" },
    { "name": "ITC Bodoni 72", "id": "itc-bodoni-72" },
    { "name": "ITF Devanagari Marathi", "id": "itf-devanagari-marathi" },
    { "name": "ITF Devanagari", "id": "itf-devanagari" },
    { "name": "Jaini Purva", "id": "jaini-purva" },
    { "name": "Jaini", "id": "jaini" },
    { "name": "Jamrul", "id": "jamrul" },
    { "name": "JasmineUPC", "id": "jasmineupc" },
    { "name": "Javanese Text", "id": "javanese-text" },
    { "name": "Jung Gothic", "id": "jung-gothic" },
    { "name": "KacstOne", "id": "kacstone" },
    { "name": "Kai", "id": "kai" },
    { "name": "Kailasa", "id": "kailasa" },
    { "name": "Kaiti SC", "id": "kaiti-sc" },
    { "name": "Kaiti TC", "id": "kaiti-tc" },
    { "name": "KaiTi", "id": "kaiti" },
    { "name": "Kalapi", "id": "kalapi" },
    { "name": "Kalinga", "id": "kalinga" },
    { "name": "Kannada MN", "id": "kannada-mn" },
    { "name": "Kannada Sangam MN", "id": "kannada-sangam-mn" },
    { "name": "Kartika", "id": "kartika" },
    { "name": "Karumbi", "id": "karumbi" },
    { "name": "Katari", "id": "katari" },
    { "name": "Kefa", "id": "kefa" },
    { "name": "Keraleeyam", "id": "keraleeyam" },
    { "name": "Keyboard", "id": "keyboard" },
    { "name": "Khmer MN", "id": "khmer-mn" },
    { "name": "Khmer OS System", "id": "khmer-os-system" },
    { "name": "Khmer OS", "id": "khmer-os" },
    { "name": "Khmer Sangam MN", "id": "khmer-sangam-mn" },
    { "name": "Khmer UI", "id": "khmer-ui" },
    { "name": "Kinnari", "id": "kinnari" },
    { "name": "KodchiangUPC", "id": "kodchiangupc" },
    { "name": "Kohinoor Bangla", "id": "kohinoor-bangla" },
    { "name": "Kohinoor Devanagari", "id": "kohinoor-devanagari" },
    { "name": "Kohinoor Telugu", "id": "kohinoor-telugu" },
    { "name": "Kokila", "id": "kokila" },
    { "name": "Kokonor", "id": "kokonor" },
    { "name": "Koufi Abjadi", "id": "koufi-abjadi" },
    { "name": "Krungthep", "id": "krungthep" },
    { "name": "Kuenstler Script", "id": "kuenstler-script" },
    { "name": "KufiStandard GK", "id": "kufistandard-gk" },
    { "name": "Lahore Gurmukhi", "id": "lahore-gurmukhi" },
    { "name": "Laimoon", "id": "laimoon" },
    { "name": "Laksaman", "id": "laksaman" },
    { "name": "Lao MN", "id": "lao-mn" },
    { "name": "Lao Sangam MN", "id": "lao-sangam-mn" },
    { "name": "Lao UI", "id": "lao-ui" },
    { "name": "LastResort", "id": "lastresort" },
    { "name": "Latha", "id": "latha" },
    { "name": "Lava Devanagari", "id": "lava-devanagari" },
    { "name": "Lava Kannada", "id": "lava-kannada" },
    { "name": "Lava Telugu", "id": "lava-telugu" },
    { "name": "Leelawadee UI", "id": "leelawadee-ui" },
    { "name": "Leelawadee", "id": "leelawadee" },
    { "name": "Levenim MT", "id": "levenim-mt" },
    { "name": "Liberation Mono", "id": "liberation-mono" },
    { "name": "Liberation Sans Narrow", "id": "liberation-sans-narrow" },
    { "name": "Liberation Sans", "id": "liberation-sans" },
    { "name": "Liberation Serif", "id": "liberation-serif" },
    { "name": "Libian SC", "id": "libian-sc" },
    { "name": "Libian TC", "id": "libian-tc" },
    { "name": "LiHei Pro", "id": "lihei-pro" },
    { "name": "Likhan", "id": "likhan" },
    { "name": "LilyUPC", "id": "lilyupc" },
    { "name": "LiSong Pro", "id": "lisong-pro" },
    { "name": "LKLUG", "id": "lklug" },
    { "name": "Lohit Assamese", "id": "lohit-assamese" },
    { "name": "Lohit Bengali", "id": "lohit-bengali" },
    { "name": "Lohit Devanagari", "id": "lohit-devanagari" },
    { "name": "Lohit Gujarati", "id": "lohit-gujarati" },
    { "name": "Lohit Gurmukhi", "id": "lohit-gurmukhi" },
    { "name": "Lohit Kannada", "id": "lohit-kannada" },
    { "name": "Lohit Malayalam", "id": "lohit-malayalam" },
    { "name": "Lohit Odia", "id": "lohit-odia" },
    { "name": "Lohit Tamil Classical", "id": "lohit-tamil-classical" },
    { "name": "Lohit Tamil", "id": "lohit-tamil" },
    { "name": "Lohit Telugu", "id": "lohit-telugu" },
    { "name": "Loma", "id": "loma" },
    { "name": "Lucida Bright", "id": "lucida-bright" },
    { "name": "Lucida Console", "id": "lucida-console" },
    { "name": "Lucida Grande", "id": "lucida-grande" },
    { "name": "Lucida Sans Unicode", "id": "lucida-sans-unicode" },
    { "name": "Lucida Sans", "id": "lucida-sans" },
    { "name": "Luminari", "id": "luminari" },
    { "name": "Maku", "id": "maku" },
    { "name": "Malayalam MN", "id": "malayalam-mn" },
    { "name": "Malayalam Sangam MN", "id": "malayalam-sangam-mn" },
    { "name": "Malgun Gothic", "id": "malgun-gothic" },
    { "name": "Mangal", "id": "mangal" },
    { "name": "Manjari", "id": "manjari" },
    { "name": "Marker Felt", "id": "marker-felt" },
    { "name": "Meera", "id": "meera" },
    { "name": "Meiryo", "id": "meiryo" },
    { "name": "Menlo", "id": "menlo" },
    { "name": "Microsoft Himalaya", "id": "microsoft-himalaya" },
    { "name": "Microsoft JhengHei", "id": "microsoft-jhenghei" },
    { "name": "Microsoft New Tai Lue", "id": "microsoft-new-tai-lue" },
    { "name": "Microsoft PhagsPa", "id": "microsoft-phagspa" },
    { "name": "Microsoft Sans Serif", "id": "microsoft-sans-serif" },
    { "name": "Microsoft Tai Le", "id": "microsoft-tai-le" },
    { "name": "Microsoft Uighur", "id": "microsoft-uighur" },
    { "name": "Microsoft YaHei", "id": "microsoft-yahei" },
    { "name": "Microsoft Yi Baiti", "id": "microsoft-yi-baiti" },
    { "name": "MingLiU", "id": "mingliu" },
    { "name": "MingLiU-ExtB", "id": "mingliu-extb" },
    { "name": "Miriam", "id": "miriam" },
    { "name": "Mishafi Gold", "id": "mishafi-gold" },
    { "name": "Mishafi", "id": "mishafi" },
    { "name": "Mitra Mono", "id": "mitra-mono" },
    { "name": "Modak", "id": "modak" },
    { "name": "Mona Lisa Solid ITC TT", "id": "mona-lisa-solid-itc-tt" },
    { "name": "Monaco CY", "id": "monaco-cy" },
    { "name": "Monaco", "id": "monaco" },
    { "name": "Mongolian Baiti", "id": "mongolian-baiti" },
    { "name": "Monotype LingWai", "id": "monotype-lingwai" },
    { "name": "MoolBoran", "id": "moolboran" },
    { "name": "mry_KacstQurn", "id": "mry_kacstqurn" },
    { "name": "MS Gothic", "id": "ms-gothic" },
    { "name": "MS Mincho", "id": "ms-mincho" },
    { "name": "Mshtakan", "id": "mshtakan" },
    { "name": "Mukta Malar", "id": "mukta-malar" },
    { "name": "Mukta Vaani", "id": "mukta-vaani" },
    { "name": "Mukta", "id": "mukta" },
    { "name": "MuktaMahee", "id": "muktamahee" },
    { "name": "Muna", "id": "muna" },
    { "name": "MV Boli", "id": "mv-boli" },
    { "name": "Myanmar MN", "id": "myanmar-mn" },
    { "name": "Myanmar Sangam MN", "id": "myanmar-sangam-mn" },
    { "name": "Myanmar Text", "id": "myanmar-text" },
    { "name": "Myriad Arabic", "id": "myriad-arabic" },
    { "name": "Nadeem", "id": "nadeem" },
    { "name": "Nakula", "id": "nakula" },
    { "name": "Nanum Brush Script", "id": "nanum-brush-script" },
    { "name": "Nanum Pen Script", "id": "nanum-pen-script" },
    { "name": "NanumGothic", "id": "nanumgothic" },
    { "name": "NanumMyeongjo", "id": "nanummyeongjo" },
    { "name": "Narkisim", "id": "narkisim" },
    { "name": "Navilu", "id": "navilu" },
    { "name": "Neue Haas Grotesk Text Pro", "id": "neue-haas-grotesk-text-pro" },
    { "name": "New Peninim MT Inclined", "id": "new-peninim-mt-inclined" },
    { "name": "New Peninim MT", "id": "new-peninim-mt" },
    { "name": "New Peninim", "id": "new-peninim" },
    { "name": "New York", "id": "new-york" },
    { "name": "Nimbus Mono L", "id": "nimbus-mono-l" },
    { "name": "Nimbus Mono PS", "id": "nimbus-mono-ps" },
    { "name": "Nimbus Roman No9 L", "id": "nimbus-roman-no9-l" },
    { "name": "Nimbus Roman", "id": "nimbus-roman" },
    { "name": "Nimbus Sans L", "id": "nimbus-sans-l" },
    { "name": "Nimbus Sans Narrow", "id": "nimbus-sans-narrow" },
    { "name": "Nimbus Sans", "id": "nimbus-sans" },
    { "name": "Nirmala UI", "id": "nirmala-ui" },
    { "name": "Nisan", "id": "nisan" },
    { "name": "NISC GB18030", "id": "nisc-gb18030" },
    { "name": "Norasi", "id": "norasi" },
    { "name": "Noteworthy", "id": "noteworthy" },
    { "name": "Noto Kufi Arabic", "id": "noto-kufi-arabic" },
    { "name": "Noto Looped Lao", "id": "noto-looped-lao" },
    { "name": "Noto Looped Thai", "id": "noto-looped-thai" },
    { "name": "Noto Mono", "id": "noto-mono" },
    { "name": "Noto Naskh Arabic", "id": "noto-naskh-arabic" },
    { "name": "Noto Nastaliq Urdu", "id": "noto-nastaliq-urdu" },
    { "name": "Noto Rashi Hebrew", "id": "noto-rashi-hebrew" },
    { "name": "Noto Sans Adlam Unjoined", "id": "noto-sans-adlam-unjoined" },
    { "name": "Noto Sans Adlam", "id": "noto-sans-adlam" },
    { "name": "Noto Sans Arabic", "id": "noto-sans-arabic" },
    { "name": "Noto Sans Armenian", "id": "noto-sans-armenian" },
    { "name": "Noto Sans Avestan", "id": "noto-sans-avestan" },
    { "name": "Noto Sans Balinese", "id": "noto-sans-balinese" },
    { "name": "Noto Sans Bamum", "id": "noto-sans-bamum" },
    { "name": "Noto Sans Bassa Vah", "id": "noto-sans-bassa-vah" },
    { "name": "Noto Sans Batak", "id": "noto-sans-batak" },
    { "name": "Noto Sans Bengali", "id": "noto-sans-bengali" },
    { "name": "Noto Sans Bhaiksuki", "id": "noto-sans-bhaiksuki" },
    { "name": "Noto Sans Brahmi", "id": "noto-sans-brahmi" },
    { "name": "Noto Sans Buginese", "id": "noto-sans-buginese" },
    { "name": "Noto Sans Buhid", "id": "noto-sans-buhid" },
    { "name": "Noto Sans Canadian Aboriginal", "id": "noto-sans-canadian-aboriginal" },
    { "name": "Noto Sans Carian", "id": "noto-sans-carian" },
    { "name": "Noto Sans Caucasian Albanian", "id": "noto-sans-caucasian-albanian" },
    { "name": "Noto Sans Chakma", "id": "noto-sans-chakma" },
    { "name": "Noto Sans Cham", "id": "noto-sans-cham" },
    { "name": "Noto Sans Cherokee", "id": "noto-sans-cherokee" },
    { "name": "Noto Sans CJK HK", "id": "noto-sans-cjk-hk" },
    { "name": "Noto Sans CJK JP", "id": "noto-sans-cjk-jp" },
    { "name": "Noto Sans CJK KR", "id": "noto-sans-cjk-kr" },
    { "name": "Noto Sans CJK SC", "id": "noto-sans-cjk-sc" },
    { "name": "Noto Sans CJK TC", "id": "noto-sans-cjk-tc" },
    { "name": "Noto Sans Coptic", "id": "noto-sans-coptic" },
    { "name": "Noto Sans Cypriot", "id": "noto-sans-cypriot" },
    { "name": "Noto Sans Deseret", "id": "noto-sans-deseret" },
    { "name": "Noto Sans Devanagari", "id": "noto-sans-devanagari" },
    { "name": "Noto Sans Display", "id": "noto-sans-display" },
    { "name": "Noto Sans Duployan", "id": "noto-sans-duployan" },
    { "name": "Noto Sans Elbasan", "id": "noto-sans-elbasan" },
    { "name": "Noto Sans Elymaic", "id": "noto-sans-elymaic" },
    { "name": "Noto Sans Ethiopic", "id": "noto-sans-ethiopic" },
    { "name": "Noto Sans Georgian", "id": "noto-sans-georgian" },
    { "name": "Noto Sans Glagolitic", "id": "noto-sans-glagolitic" },
    { "name": "Noto Sans Gothic", "id": "noto-sans-gothic" },
    { "name": "Noto Sans Grantha", "id": "noto-sans-grantha" },
    { "name": "Noto Sans Gujarati", "id": "noto-sans-gujarati" },
    { "name": "Noto Sans Gunjala Gondi", "id": "noto-sans-gunjala-gondi" },
    { "name": "Noto Sans Gurmukhi", "id": "noto-sans-gurmukhi" },
    { "name": "Noto Sans Hanifi Rohingya", "id": "noto-sans-hanifi-rohingya" },
    { "name": "Noto Sans Hanunoo", "id": "noto-sans-hanunoo" },
    { "name": "Noto Sans Hatran", "id": "noto-sans-hatran" },
    { "name": "Noto Sans Hebrew", "id": "noto-sans-hebrew" },
    { "name": "Noto Sans Imperial Aramaic", "id": "noto-sans-imperial-aramaic" },
    { "name": "Noto Sans Javanese", "id": "noto-sans-javanese" },
    { "name": "Noto Sans Kaithi", "id": "noto-sans-kaithi" },
    { "name": "Noto Sans Kannada", "id": "noto-sans-kannada" },
    { "name": "Noto Sans Kayah Li", "id": "noto-sans-kayah-li" },
    { "name": "Noto Sans Kharoshthi", "id": "noto-sans-kharoshthi" },
    { "name": "Noto Sans Khmer", "id": "noto-sans-khmer" },
    { "name": "Noto Sans Khojki", "id": "noto-sans-khojki" },
    { "name": "Noto Sans Khudawadi", "id": "noto-sans-khudawadi" },
    { "name": "Noto Sans Lao", "id": "noto-sans-lao" },
    { "name": "Noto Sans Lepcha", "id": "noto-sans-lepcha" },
    { "name": "Noto Sans Limbu", "id": "noto-sans-limbu" },
    { "name": "Noto Sans Lisu", "id": "noto-sans-lisu" },
    { "name": "Noto Sans Lycian", "id": "noto-sans-lycian" },
    { "name": "Noto Sans Lydian", "id": "noto-sans-lydian" },
    { "name": "Noto Sans Mahajani", "id": "noto-sans-mahajani" },
    { "name": "Noto Sans Malayalam", "id": "noto-sans-malayalam" },
    { "name": "Noto Sans Mandaic", "id": "noto-sans-mandaic" },
    { "name": "Noto Sans Manichaean", "id": "noto-sans-manichaean" },
    { "name": "Noto Sans Marchen", "id": "noto-sans-marchen" },
    { "name": "Noto Sans Masaram Gondi", "id": "noto-sans-masaram-gondi" },
    { "name": "Noto Sans Mayan Numerals", "id": "noto-sans-mayan-numerals" },
    { "name": "Noto Sans Medefaidrin", "id": "noto-sans-medefaidrin" },
    { "name": "Noto Sans Meetei Mayek", "id": "noto-sans-meetei-mayek" },
    { "name": "Noto Sans Mende Kikakui", "id": "noto-sans-mende-kikakui" },
    { "name": "Noto Sans Meroitic", "id": "noto-sans-meroitic" },
    { "name": "Noto Sans Miao", "id": "noto-sans-miao" },
    { "name": "Noto Sans Modi", "id": "noto-sans-modi" },
    { "name": "Noto Sans Mongolian", "id": "noto-sans-mongolian" },
    { "name": "Noto Sans Mono CJK HK", "id": "noto-sans-mono-cjk-hk" },
    { "name": "Noto Sans Mono CJK JP", "id": "noto-sans-mono-cjk-jp" },
    { "name": "Noto Sans Mono CJK KR", "id": "noto-sans-mono-cjk-kr" },
    { "name": "Noto Sans Mono CJK SC", "id": "noto-sans-mono-cjk-sc" },
    { "name": "Noto Sans Mono CJK TC", "id": "noto-sans-mono-cjk-tc" },
    { "name": "Noto Sans Mro", "id": "noto-sans-mro" },
    { "name": "Noto Sans Multani", "id": "noto-sans-multani" },
    { "name": "Noto Sans Myanmar", "id": "noto-sans-myanmar" },
    { "name": "Noto Sans Nabataean", "id": "noto-sans-nabataean" },
    { "name": "Noto Sans New Tai Lue", "id": "noto-sans-new-tai-lue" },
    { "name": "Noto Sans Newa", "id": "noto-sans-newa" },
    { "name": "Noto Sans NKo", "id": "noto-sans-nko" },
    { "name": "Noto Sans Nushu", "id": "noto-sans-nushu" },
    { "name": "Noto Sans Ogham", "id": "noto-sans-ogham" },
    { "name": "Noto Sans Ol Chiki", "id": "noto-sans-ol-chiki" },
    { "name": "Noto Sans Oriya", "id": "noto-sans-oriya" },
    { "name": "Noto Sans Osage", "id": "noto-sans-osage" },
    { "name": "Noto Sans Osmanya", "id": "noto-sans-osmanya" },
    { "name": "Noto Sans Pahawh Hmong", "id": "noto-sans-pahawh-hmong" },
    { "name": "Noto Sans Palmyrene", "id": "noto-sans-palmyrene" },
    { "name": "Noto Sans Pau Cin Hau", "id": "noto-sans-pau-cin-hau" },
    { "name": "Noto Sans PhagsPa", "id": "noto-sans-phagspa" },
    { "name": "Noto Sans Rejang", "id": "noto-sans-rejang" },
    { "name": "Noto Sans Runic", "id": "noto-sans-runic" },
    { "name": "Noto Sans Samaritan", "id": "noto-sans-samaritan" },
    { "name": "Noto Sans Saurashtra", "id": "noto-sans-saurashtra" },
    { "name": "Noto Sans Sharada", "id": "noto-sans-sharada" },
    { "name": "Noto Sans Shavian", "id": "noto-sans-shavian" },
    { "name": "Noto Sans Siddham", "id": "noto-sans-siddham" },
    { "name": "Noto Sans Sinhala", "id": "noto-sans-sinhala" },
    { "name": "Noto Sans Sogdian", "id": "noto-sans-sogdian" },
    { "name": "Noto Sans Sora Sompeng", "id": "noto-sans-sora-sompeng" },
    { "name": "Noto Sans Soyombo", "id": "noto-sans-soyombo" },
    { "name": "Noto Sans Sundanese", "id": "noto-sans-sundanese" },
    { "name": "Noto Sans Syloti Nagri", "id": "noto-sans-syloti-nagri" },
    { "name": "Noto Sans Syriac", "id": "noto-sans-syriac" },
    { "name": "Noto Sans Tagalog", "id": "noto-sans-tagalog" },
    { "name": "Noto Sans Tagbanwa", "id": "noto-sans-tagbanwa" },
    { "name": "Noto Sans Tai Le", "id": "noto-sans-tai-le" },
    { "name": "Noto Sans Tai Tham", "id": "noto-sans-tai-tham" },
    { "name": "Noto Sans Tai Viet", "id": "noto-sans-tai-viet" },
    { "name": "Noto Sans Takri", "id": "noto-sans-takri" },
    { "name": "Noto Sans Tamil Supplement", "id": "noto-sans-tamil-supplement" },
    { "name": "Noto Sans Tamil", "id": "noto-sans-tamil" },
    { "name": "Noto Sans Telugu", "id": "noto-sans-telugu" },
    { "name": "Noto Sans Thaana", "id": "noto-sans-thaana" },
    { "name": "Noto Sans Thai", "id": "noto-sans-thai" },
    { "name": "Noto Sans Tifinagh Adrar", "id": "noto-sans-tifinagh-adrar" },
    { "name": "Noto Sans Tifinagh Agraw Imazighen", "id": "noto-sans-tifinagh-agraw-imazighen" },
    { "name": "Noto Sans Tifinagh Ahaggar", "id": "noto-sans-tifinagh-ahaggar" },
    { "name": "Noto Sans Tifinagh Air", "id": "noto-sans-tifinagh-air" },
    { "name": "Noto Sans Tifinagh APT", "id": "noto-sans-tifinagh-apt" },
    { "name": "Noto Sans Tifinagh Azawagh", "id": "noto-sans-tifinagh-azawagh" },
    { "name": "Noto Sans Tifinagh Ghat", "id": "noto-sans-tifinagh-ghat" },
    { "name": "Noto Sans Tifinagh Hawad", "id": "noto-sans-tifinagh-hawad" },
    { "name": "Noto Sans Tifinagh Rhissa Ixa", "id": "noto-sans-tifinagh-rhissa-ixa" },
    { "name": "Noto Sans Tifinagh SIL", "id": "noto-sans-tifinagh-sil" },
    { "name": "Noto Sans Tifinagh Tawellemmet", "id": "noto-sans-tifinagh-tawellemmet" },
    { "name": "Noto Sans Tifinagh", "id": "noto-sans-tifinagh" },
    { "name": "Noto Sans Tirhuta", "id": "noto-sans-tirhuta" },
    { "name": "Noto Sans Ugaritic", "id": "noto-sans-ugaritic" },
    { "name": "Noto Sans Vai", "id": "noto-sans-vai" },
    { "name": "Noto Sans Wancho", "id": "noto-sans-wancho" },
    { "name": "Noto Sans Warang Citi", "id": "noto-sans-warang-citi" },
    { "name": "Noto Sans Yi", "id": "noto-sans-yi" },
    { "name": "Noto Sans Zanabazar Square", "id": "noto-sans-zanabazar-square" },
    { "name": "Noto Sans", "id": "noto-sans" },
    { "name": "Noto Serif Ahom", "id": "noto-serif-ahom" },
    { "name": "Noto Serif Armenian", "id": "noto-serif-armenian" },
    { "name": "Noto Serif Balinese", "id": "noto-serif-balinese" },
    { "name": "Noto Serif Bengali", "id": "noto-serif-bengali" },
    { "name": "Noto Serif CJK JP", "id": "noto-serif-cjk-jp" },
    { "name": "Noto Serif CJK KR", "id": "noto-serif-cjk-kr" },
    { "name": "Noto Serif CJK SC", "id": "noto-serif-cjk-sc" },
    { "name": "Noto Serif CJK TC", "id": "noto-serif-cjk-tc" },
    { "name": "Noto Serif Devanagari", "id": "noto-serif-devanagari" },
    { "name": "Noto Serif Display", "id": "noto-serif-display" },
    { "name": "Noto Serif Dogra", "id": "noto-serif-dogra" },
    { "name": "Noto Serif Ethiopic", "id": "noto-serif-ethiopic" },
    { "name": "Noto Serif Georgian", "id": "noto-serif-georgian" },
    { "name": "Noto Serif Grantha", "id": "noto-serif-grantha" },
    { "name": "Noto Serif Gujarati", "id": "noto-serif-gujarati" },
    { "name": "Noto Serif Gurmukhi", "id": "noto-serif-gurmukhi" },
    { "name": "Noto Serif Hebrew", "id": "noto-serif-hebrew" },
    { "name": "Noto Serif Hmong Nyiakeng", "id": "noto-serif-hmong-nyiakeng" },
    { "name": "Noto Serif Kannada", "id": "noto-serif-kannada" },
    { "name": "Noto Serif Khmer", "id": "noto-serif-khmer" },
    { "name": "Noto Serif Khojki", "id": "noto-serif-khojki" },
    { "name": "Noto Serif Lao", "id": "noto-serif-lao" },
    { "name": "Noto Serif Malayalam", "id": "noto-serif-malayalam" },
    { "name": "Noto Serif Myanmar", "id": "noto-serif-myanmar" },
    { "name": "Noto Serif Sinhala", "id": "noto-serif-sinhala" },
    { "name": "Noto Serif Tamil", "id": "noto-serif-tamil" },
    { "name": "Noto Serif Tangut", "id": "noto-serif-tangut" },
    { "name": "Noto Serif Telugu", "id": "noto-serif-telugu" },
    { "name": "Noto Serif Thai", "id": "noto-serif-thai" },
    { "name": "Noto Serif Tibetan", "id": "noto-serif-tibetan" },
    { "name": "Noto Serif Yezidi", "id": "noto-serif-yezidi" },
    { "name": "Noto Serif", "id": "noto-serif" },
    { "name": "Noto Traditional Nushu", "id": "noto-traditional-nushu" },
    { "name": "Nyala", "id": "nyala" },
    { "name": "October Devanagari", "id": "october-devanagari" },
    { "name": "October Tamil", "id": "october-tamil" },
    { "name": "Open Sans", "id": "open-sans" },
    { "name": "Optima", "id": "optima" },
    { "name": "Oriya MN", "id": "oriya-mn" },
    { "name": "Oriya Sangam MN", "id": "oriya-sangam-mn" },
    { "name": "Osaka", "id": "osaka" },
    { "name": "Osaka-Mono", "id": "osaka-mono" },
    { "name": "Palatino Linotype", "id": "palatino-linotype" },
    { "name": "Palatino", "id": "palatino" },
    { "name": "Papyrus", "id": "papyrus" },
    { "name": "PC Myungjo", "id": "pc-myungjo" },
    { "name": "Phosphate", "id": "phosphate" },
    { "name": "PilGi", "id": "pilgi" },
    { "name": "Pilgiche", "id": "pilgiche" },
    { "name": "PingFang HK", "id": "pingfang-hk" },
    { "name": "PingFang SC", "id": "pingfang-sc" },
    { "name": "PingFang TC", "id": "pingfang-tc" },
    { "name": "Plantagenet Cherokee", "id": "plantagenet-cherokee" },
    { "name": "PortagoITC TT", "id": "portagoitc-tt" },
    { "name": "Pothana2000", "id": "pothana2000" },
    { "name": "Princetown LET", "id": "princetown-let" },
    { "name": "Produkt", "id": "produkt" },
    { "name": "Proxima Nova", "id": "proxima-nova" },
    { "name": "PSL Ornanong Pro", "id": "psl-ornanong-pro" },
    { "name": "PT Mono", "id": "pt-mono" },
    { "name": "PT Sans Narrow", "id": "pt-sans-narrow" },
    { "name": "PT Sans", "id": "pt-sans" },
    { "name": "PT Serif", "id": "pt-serif" },
    { "name": "Publico Headline Roman", "id": "publico-headline-roman" },
    { "name": "Purisa", "id": "purisa" },
    { "name": "Quotes Caps", "id": "quotes-caps" },
    { "name": "Quotes Script", "id": "quotes-script" },
    { "name": "Raanana", "id": "raanana" },
    { "name": "Raavi", "id": "raavi" },
    { "name": "Rachana", "id": "rachana" },
    { "name": "RaghuMalayalamSans", "id": "raghumalayalamsans" },
    { "name": "Rasa", "id": "rasa" },
    { "name": "Raya", "id": "raya" },
    { "name": "Roboto", "id": "roboto" },
    { "name": "Rockwell Nova", "id": "rockwell-nova" },
    { "name": "Rockwell", "id": "rockwell" },
    { "name": "Rod", "id": "rod" },
    { "name": "Saab", "id": "saab" },
    { "name": "Sahadeva", "id": "sahadeva" },
    { "name": "Sakkal Majalla", "id": "sakkal-majalla" },
    { "name": "Sama Devanagari", "id": "sama-devanagari" },
    { "name": "Sama Gujarati", "id": "sama-gujarati" },
    { "name": "Sama Gurmukhi", "id": "sama-gurmukhi" },
    { "name": "Sama Kannada", "id": "sama-kannada" },
    { "name": "Sama Malayalam", "id": "sama-malayalam" },
    { "name": "Sama Tamil", "id": "sama-tamil" },
    { "name": "Samanata", "id": "samanata" },
    { "name": "Samyak Devanagari", "id": "samyak-devanagari" },
    { "name": "Samyak Gujarati", "id": "samyak-gujarati" },
    { "name": "Samyak Tamil", "id": "samyak-tamil" },
    { "name": "San Francisco Mono", "id": "san-francisco-mono" },
    { "name": "Sana", "id": "sana" },
    { "name": "Sand", "id": "sand" },
    { "name": "Sanskrit Text", "id": "sanskrit-text" },
    { "name": "Sarai", "id": "sarai" },
    { "name": "Sathu", "id": "sathu" },
    { "name": "Sauber Script", "id": "sauber-script" },
    { "name": "Sawasdee", "id": "sawasdee" },
    { "name": "SchoolHouse Cursive B", "id": "schoolhouse-cursive-b" },
    { "name": "SchoolHouse Printed A", "id": "schoolhouse-printed-a" },
    { "name": "Segoe Print", "id": "segoe-print" },
    { "name": "Segoe Script", "id": "segoe-script" },
    { "name": "Segoe UI", "id": "segoe-ui" },
    { "name": "Seoul", "id": "seoul" },
    { "name": "SF Arabic", "id": "sf-arabic" },
    { "name": "SF Compact", "id": "sf-compact" },
    { "name": "SF Mono", "id": "sf-mono" },
    { "name": "SF Pro Display", "id": "sf-pro-display" },
    { "name": "SF Pro Text", "id": "sf-pro-text" },
    { "name": "SF Pro", "id": "sf-pro" },
    { "name": "Shin Myungjo Neue", "id": "shin-myungjo-neue" },
    { "name": "Shobhika", "id": "shobhika" },
    { "name": "Shonar Bangla", "id": "shonar-bangla" },
    { "name": "Shree Devanagari 714", "id": "shree-devanagari-714" },
    { "name": "Shruti", "id": "shruti" },
    { "name": "SignPainter", "id": "signpainter" },
    { "name": "SignPainter-HouseScript", "id": "signpainter-housescript" },
    { "name": "Silom", "id": "silom" },
    { "name": "SimHei", "id": "simhei" },
    { "name": "Simplified Arabic", "id": "simplified-arabic" },
    { "name": "SimSong", "id": "simsong" },
    { "name": "SimSun", "id": "simsun" },
    { "name": "Sinhala MN", "id": "sinhala-mn" },
    { "name": "Sinhala Sangam MN", "id": "sinhala-sangam-mn" },
    { "name": "Sitka", "id": "sitka" },
    { "name": "Skia", "id": "skia" },
    { "name": "Snell Roundhand", "id": "snell-roundhand" },
    { "name": "Somer", "id": "somer" },
    { "name": "Songti SC", "id": "songti-sc" },
    { "name": "Songti TC", "id": "songti-tc" },
    { "name": "Spot Mono", "id": "spot-mono" },
    { "name": "ST FangSong", "id": "st-fangsong" },
    { "name": "ST Heiti", "id": "st-heiti" },
    { "name": "ST Kaiti", "id": "st-kaiti" },
    { "name": "ST Song", "id": "st-song" },
    { "name": "ST Xihei", "id": "st-xihei" },
    { "name": "STIX Two Text", "id": "stix-two-text" },
    { "name": "STIXGeneral-Regular", "id": "stixgeneral-regular" },
    { "name": "Stone Sans Sem ITC TT", "id": "stone-sans-sem-itc-tt" },
    { "name": "Sukhumvit Set Text", "id": "sukhumvit-set-text" },
    { "name": "Sylfaen", "id": "sylfaen" },
    { "name": "Synchro LET", "id": "synchro-let" },
    { "name": "Tae Graphic", "id": "tae-graphic" },
    { "name": "Tahoma", "id": "tahoma" },
    { "name": "Taipei", "id": "taipei" },
    { "name": "Tamil MN", "id": "tamil-mn" },
    { "name": "Tamil Sangam MN", "id": "tamil-sangam-mn" },
    { "name": "Techno", "id": "techno" },
    { "name": "Telugu MN", "id": "telugu-mn" },
    { "name": "Telugu Sangam MN", "id": "telugu-sangam-mn" },
    { "name": "Textile", "id": "textile" },
    { "name": "Thonburi", "id": "thonburi" },
    { "name": "Tibetan Machine Uni", "id": "tibetan-machine-uni" },
    { "name": "Times CY", "id": "times-cy" },
    { "name": "Times New Roman", "id": "times-new-roman" },
    { "name": "Times Roman", "id": "times-roman" },
    { "name": "Times", "id": "times" },
    { "name": "Tiro Bangla", "id": "tiro-bangla" },
    { "name": "Tiro Devanagari Hindi", "id": "tiro-devanagari-hindi" },
    { "name": "Tiro Devanagari Marathi", "id": "tiro-devanagari-marathi" },
    { "name": "Tiro Devanagari Sanskrit", "id": "tiro-devanagari-sanskrit" },
    { "name": "Tiro Gurmukhi", "id": "tiro-gurmukhi" },
    { "name": "Tiro Hindi", "id": "tiro-hindi" },
    { "name": "Tiro Kannada", "id": "tiro-kannada" },
    { "name": "Tiro Marathi", "id": "tiro-marathi" },
    { "name": "Tiro Sanskrit", "id": "tiro-sanskrit" },
    { "name": "Tiro Tamil", "id": "tiro-tamil" },
    { "name": "Tiro Telugu", "id": "tiro-telugu" },
    { "name": "Tlwg Mono", "id": "tlwg-mono" },
    { "name": "Tlwg Typewriter", "id": "tlwg-typewriter" },
    { "name": "Tlwg Typist", "id": "tlwg-typist" },
    { "name": "Tlwg Typo", "id": "tlwg-typo" },
    { "name": "Toppan Bunkyu Gothic", "id": "toppan-bunkyu-gothic" },
    { "name": "Toppan Bunkyu Mincho", "id": "toppan-bunkyu-mincho" },
    { "name": "Traditional Arabic", "id": "traditional-arabic" },
    { "name": "Trattatello", "id": "trattatello" },
    { "name": "Trebuchet MS", "id": "trebuchet-ms" },
    { "name": "Tsukushi A Round Gothic", "id": "tsukushi-a-round-gothic" },
    { "name": "Tsukushi B Round Gothic", "id": "tsukushi-b-round-gothic" },
    { "name": "Tunga", "id": "tunga" },
    { "name": "Tw Cen MT", "id": "tw-cen-mt" },
    { "name": "Ubuntu Condensed", "id": "ubuntu-condensed" },
    { "name": "Ubuntu Mono", "id": "ubuntu-mono" },
    { "name": "Ubuntu", "id": "ubuntu" },
    { "name": "UD Digi Kyokasho", "id": "ud-digi-kyokasho" },
    { "name": "Umpush", "id": "umpush" },
    { "name": "Urdu Typesetting", "id": "urdu-typesetting" },
    { "name": "Uroob", "id": "uroob" },
    { "name": "URW Palladio L", "id": "urw-palladio-l" },
    { "name": "Utsaah", "id": "utsaah" },
    { "name": "Vani", "id": "vani" },
    { "name": "Vemana2000", "id": "vemana2000" },
    { "name": "Verdana Pro", "id": "verdana-pro" },
    { "name": "Verdana", "id": "verdana" },
    { "name": "Vijaya", "id": "vijaya" },
    { "name": "Vrinda", "id": "vrinda" },
    { "name": "Waree", "id": "waree" },
    { "name": "Waseem", "id": "waseem" },
    { "name": "Wawati SC", "id": "wawati-sc" },
    { "name": "Wawati TC", "id": "wawati-tc" },
    { "name": "Yaziji", "id": "yaziji" },
    { "name": "Yrsa", "id": "yrsa" },
    { "name": "Yu Gothic", "id": "yu-gothic" },
    { "name": "Yu Kyokasho N", "id": "yu-kyokasho-n" },
    { "name": "Yu Mincho", "id": "yu-mincho" },
    { "name": "Yuanti SC", "id": "yuanti-sc" },
    { "name": "Yuanti TC", "id": "yuanti-tc" },
    { "name": "Yuppy SC", "id": "yuppy-sc" },
    { "name": "Zapf Chancery", "id": "zapf-chancery" },
    { "name": "Zapfino", "id": "zapfino" }
]